MANIFEST.in
README.txt
setup.py
NoseJS.egg-info/PKG-INFO
NoseJS.egg-info/SOURCES.txt
NoseJS.egg-info/dependency_links.txt
NoseJS.egg-info/entry_points.txt
NoseJS.egg-info/not-zip-safe
NoseJS.egg-info/requires.txt
NoseJS.egg-info/top_level.txt
nosejs/__init__.py
nosejs/java.py
nosejs/lint.py
nosejs/nosejs.py
nosejs/resources/__nosejs__.html
nosejs/resources/__nosejs__.js
nosejs/resources/env.js
nosejs/resources/env.js.README.txt
nosejs/resources/jquery-1.3.1.js
nosejs/resources/rhino-testrunner.js
nosejs/resources/jquery/qunit-testrunner.js