Metadata-Version: 1.0
Name: NoseJS
Version: 0.9.4
Summary: A Nose plugin for integrating JavaScript tests into a Python test suite.
Home-page: UNKNOWN
Author: UNKNOWN
Author-email: UNKNOWN
License: UNKNOWN
Platform: UNKNOWN
